variantfinder/ParseAlignments/VariantCounter.py
variantfinder/ParseAlignments/VariantLooker.py
variantfinder/ReadFiles/DataCollector.py
variantfinder/ReadFiles/LookingForVCF.py
variantfinder/ReadFiles/VcfReader.py
variantfinder/WriteFiles/BamWriter.py
variantfinder/WriteFiles/TsvWriter.py
variantfinder/WriteFiles/VcfWriter.py
variantfinder/__init__.py
variantfinder/__main__.py
variantfinder/pyproject.toml
variantfinder-0.5.dist-info/entry_points.txt
variantfinder-0.5.dist-info/WHEEL
variantfinder-0.5.dist-info/METADATA
variantfinder-0.5.dist-info/RECORD
